wbg/core/__init__.py
wbg/core/cli.py
wbg/core/env.py
wbg/core/holidays.py
wbg/core/log_config.py
wbg/core/py.typed
wbg/core/shell.py
wbg_core-1.0.0.dist-info/METADATA
wbg_core-1.0.0.dist-info/WHEEL
wbg_core-1.0.0.dist-info/top_level.txt
wbg_core-1.0.0.dist-info/RECORD
