Metadata-Version: 2.1
Name: wbg-core
Version: 1.0.0
Requires-Python: >=3.11
Requires-Dist: pandas
